foldersizes/__init__.py
foldersizes/filesizze.py
FolderSizes-0.1.5.dist-info/LICENSE
FolderSizes-0.1.5.dist-info/METADATA
FolderSizes-0.1.5.dist-info/WHEEL
FolderSizes-0.1.5.dist-info/entry_points.txt
FolderSizes-0.1.5.dist-info/top_level.txt
FolderSizes-0.1.5.dist-info/RECORD
