Metadata-Version: 2.1
Name: FolderSizes
Version: 0.1.5
Summary: A simple script to list folder sizes
Home-page: https://github.com/cartaR02/FolderSizes
Author: Carter Struck
Author-email: carterstruckm@gmail.com
License: MIT
Classifier: Programming Language :: Python :: 3
Classifier: License :: OSI Approved :: MIT License
Classifier: Operating System :: OS Independent
License-File: LICENSE
Requires-Dist: click
